<?xml version="1.0" encoding="utf-8" ?>
<dwsync>
<file name="CBV05-01.jpg" local="128043900000000000" remote="128043900000000000" testing="0" />
<file name="CBV05-03.jpg" local="128043900000000000" remote="128043900000000000" testing="0" />
<file name="CBV05-06.jpg" local="128043900000000000" remote="128043900000000000" testing="0" />
<file name="CBV05-08.jpg" local="128043900000000000" remote="128043900000000000" testing="0" />
<file name="CBV05-10.jpg" local="128043900000000000" remote="128043900000000000" testing="0" />
<file name="CBV05-12.jpg" local="128043900000000000" remote="128043900000000000" testing="0" />
<file name="CBV05-13.jpg" local="128043900000000000" remote="128043900000000000" testing="0" />
<file name="CBV05-16.jpg" local="128043900000000000" remote="128043900000000000" testing="0" />
<file name="next.gif" local="128043900000000000" remote="128043900000000000" testing="0" />
<file name="nextdis.gif" local="128043900000000000" remote="128043900000000000" testing="0" />
<file name="prev.gif" local="128043900000000000" remote="128043900000000000" testing="0" />
<file name="prevdis.gif" local="128043900000000000" remote="128043900000000000" testing="0" />
<file name="real.htm" local="128306384400000000" remote="128306384400000000" testing="0" />
<file name="real_p.htm" local="128356207800000000" remote="128356207800000000" testing="0" />
<file name="real_x.htm" local="128043900000000000" remote="128043900000000000" testing="0" />
<file name="sldshow.js" local="128043900000000000" remote="128043900000000000" testing="0" />
</dwsync>